__init__.py
plot.py
barplotme-0.0.2.dist-info/LICENSE
barplotme-0.0.2.dist-info/METADATA
barplotme-0.0.2.dist-info/WHEEL
barplotme-0.0.2.dist-info/entry_points.txt
barplotme-0.0.2.dist-info/top_level.txt
barplotme-0.0.2.dist-info/RECORD
