Metadata-Version: 2.2
Name: barplotme
Version: 0.0.2
Summary: Create beautiful bar plots of nice numbers
Author-email: Mathias Zinnen <mathias.zinnen@gmail.com>
License:                                  Apache License
Project-URL: Homepage, https://github.com/mathiaszinnen/barplotme
Classifier: Programming Language :: Python :: 3
Classifier: Operating System :: OS Independent
License-File: LICENSE
